.gitignore
LICENSE
MANIFEST.in
README.md
requirements.txt
setup.cfg
setup.py
tox.ini
.github/workflows/test_and_deploy.yml
docs/Makefile
docs/conf.py
docs/index.rst
docs/make.bat
platelet_unet_watershed.egg-info/PKG-INFO
platelet_unet_watershed.egg-info/SOURCES.txt
platelet_unet_watershed.egg-info/dependency_links.txt
platelet_unet_watershed.egg-info/entry_points.txt
platelet_unet_watershed.egg-info/requires.txt
platelet_unet_watershed.egg-info/top_level.txt
plateseg/__init__.py
plateseg/_dock_widget.py
plateseg/predict.py
plateseg/unet.py
plateseg/watershed.py
plateseg/_tests/__init__.py
plateseg/_tests/test_dock_widget.py
plateseg/data/unet-210913-zyxmc.pt