Metadata-Version: 2.1
Name: platelet-unet-watershed
Version: 0.0.3
Summary: Segment platelets with pretrained unet and affinity watershed
Home-page: https://github.com/jni/platelet-unet-watershed
Author: Juan Nunez-Iglesias & Abigail McGovern
Author-email: juan.nunez-iglesias@monash.edu
License: BSD-3
Project-URL: Bug Tracker, https://github.com/jni/platelet-unet-watershed/issues
Project-URL: Documentation, https://github.com/jni/platelet-unet-watershed#README.md
Project-URL: Source Code, https://github.com/jni/platelet-unet-watershed
Project-URL: User Support, https://github.com/jni/platelet-unet-watershed/issues
Platform: UNKNOWN
Classifier: Development Status :: 2 - Pre-Alpha
Classifier: Intended Audience :: Developers
Classifier: Framework :: napari
Classifier: Topic :: Software Development :: Testing
Classifier: Programming Language :: Python
Classifier: Programming Language :: Python :: 3
Classifier: Programming Language :: Python :: 3.7
Classifier: Programming Language :: Python :: 3.8
Classifier: Programming Language :: Python :: 3.9
Classifier: Operating System :: OS Independent
Classifier: License :: OSI Approved :: BSD License
Requires-Python: >=3.7
License-File: LICENSE
